embeddb/__init__.py
embeddb/embeddb.py
embeddb/tests/__init__.py
embeddb/tests/test_embeddb.py
embeddb/tests/test_embeddings.py
embeddb-0.2.0.dist-info/LICENSE
embeddb-0.2.0.dist-info/METADATA
embeddb-0.2.0.dist-info/WHEEL
embeddb-0.2.0.dist-info/top_level.txt
embeddb-0.2.0.dist-info/RECORD
