Metadata-Version: 2.2
Name: embeddb
Version: 0.2.0
Summary: Tiny semantic search DB in one file. Zero config. Instant prototyping.
Home-page: https://github.com/yourusername/embeddb
Author: EmbedDB Team
Author-email: info@embeddb.example.com
Classifier: Programming Language :: Python :: 3
Classifier: Programming Language :: Python :: 3.9
Classifier: Programming Language :: Python :: 3.10
Classifier: Programming Language :: Python :: 3.11
Classifier: Programming Language :: Python :: 3.12
Classifier: License :: OSI Approved :: MIT License
Classifier: Operating System :: OS Independent
Classifier: Topic :: Database
Classifier: Topic :: Scientific/Engineering :: Artificial Intelligence
Requires-Python: >=3.9
License-File: LICENSE
Provides-Extra: embeddings
Requires-Dist: sentence-transformers>=2.0.0; extra == "embeddings"
Dynamic: author
Dynamic: author-email
Dynamic: classifier
Dynamic: description
Dynamic: description-content-type
Dynamic: home-page
Dynamic: provides-extra
Dynamic: requires-python
Dynamic: summary
